gcil/__init__.py
gcil/__main__.py
gcil/cli/__init__.py
gcil/cli/entrypoint.py
gcil/cli/main.py
gcil/engines/__init__.py
gcil/engines/base.py
gcil/engines/docker.py
gcil/engines/engine.py
gcil/engines/podman.py
gcil/features/__init__.py
gcil/features/configurations.py
gcil/features/images.py
gcil/features/menus.py
gcil/features/pipelines.py
gcil/jobs/__init__.py
gcil/jobs/outputs.py
gcil/jobs/runner.py
gcil/jobs/scripts.py
gcil/models/__init__.py
gcil/models/flags.py
gcil/models/images.py
gcil/models/jobs.py
gcil/models/options.py
gcil/models/pipelines.py
gcil/models/scripts.py
gcil/models/services.py
gcil/models/settings.py
gcil/models/stages.py
gcil/models/tags.py
gcil/models/variables.py
gcil/package/__init__.py
gcil/package/bundle.py
gcil/package/settings.py
gcil/package/updates.py
gcil/package/version.py
gcil/parsers/__init__.py
gcil/parsers/gitlab.py
gcil/parsers/parsers.py
gcil/prints/__init__.py
gcil/prints/boxes.py
gcil/prints/colors.py
gcil/prints/histories.py
gcil/prints/themes.py
gcil/system/__init__.py
gcil/system/git.py
gcil/system/notify.py
gcil/system/platform.py
gcil/system/xauth.py
gcil/types/__init__.py
gcil/types/environment.py
gcil/types/files.py
gcil/types/lists.py
gcil/types/paths.py
gcil/types/strings.py
gcil/types/volumes.py
gcil/types/yaml.py
gitlabci_local-13.0.2.dist-info/licenses/LICENSE
gitlabci_local-13.0.2.dist-info/METADATA
gitlabci_local-13.0.2.dist-info/WHEEL
gitlabci_local-13.0.2.dist-info/entry_points.txt
gitlabci_local-13.0.2.dist-info/top_level.txt
gitlabci_local-13.0.2.dist-info/RECORD
